{
  "num_clusters": 8,
  "num_rows": 4,
  "degree": 4,
  "num_iters": 6,
  "bit_width": 8,
  "bound_width": 13,
  "coeff_width": 8,
  "acc_width": 24,
  "block_size": 2,
  "num_blocks": 2,
  "data_width": 11,
  "src_idx_width": 5,
  "tail_bound": 1,
  "replay_digit_idx": 10,
  "template_memh": "MSDF_iterative_solver/generated/rtl_vectors/jacobi32_global/templates.memh",
  "cert_memh": "MSDF_iterative_solver/generated/rtl_vectors/jacobi32_global/cert_params.memh",
  "iterations": [
    {
      "iter": 0,
      "clusters": [
        {
          "state_p_rows": [
            6,
            5,
            12,
            9
          ],
          "state_n_rows": [
            4,
            10,
            24,
            18
          ],
          "abs_upper_rows": [
            3,
            6,
            13,
            10
          ],
          "block_bounds": [
            6,
            13
          ],
          "max_error": 101,
          "certified": 1,
          "packed": {
            "state_p_rows": 77359753222,
            "state_n_rows": 154719506436,
            "abs_upper_rows": 5498430603267,
            "block_bounds": 106502
          }
        },
        {
          "state_p_rows": [
            10,
            29,
            57,
            15
          ],
          "state_n_rows": [
            20,
            18,
            34,
            10
          ],
          "abs_upper_rows": [
            11,
            12,
            24,
            6
          ],
          "block_bounds": [
            12,
            24
          ],
          "max_error": 144,
          "certified": 1,
          "packed": {
            "state_p_rows": 129088153610,
            "state_n_rows": 86041989140,
            "abs_upper_rows": 3300145594379,
            "block_bounds": 196620
          }
        },
        {
          "state_p_rows": [
            27,
            30,
            3,
            10
          ],
          "state_n_rows": [
            18,
            20,
            2,
            20
          ],
          "abs_upper_rows": [
            10,
            11,
            2,
            11
          ],
          "block_bounds": [
            11,
            11
          ],
          "max_error": 154,
          "certified": 1,
          "packed": {
            "state_p_rows": 85911990299,
            "state_n_rows": 171807121426,
            "abs_upper_rows": 6047448260618,
            "block_bounds": 90123
          }
        },
        {
          "state_p_rows": [
            18,
            18,
            27,
            39
          ],
          "state_n_rows": [
            4,
            4,
            18,
            10
          ],
          "abs_upper_rows": [
            15,
            15,
            10,
            30
          ],
          "block_bounds": [
            15,
            30
          ],
          "max_error": 315,
          "certified": 1,
          "packed": {
            "state_p_rows": 335120732178,
            "state_n_rows": 85974851588,
            "abs_upper_rows": 16493345628175,
            "block_bounds": 245775
          }
        },
        {
          "state_p_rows": [
            33,
            0,
            10,
            12
          ],
          "state_n_rows": [
            2,
            0,
            4,
            8
          ],
          "abs_upper_rows": [
            32,
            1,
            7,
            5
          ],
          "block_bounds": [
            32,
            7
          ],
          "max_error": 245,
          "certified": 1,
          "packed": {
            "state_p_rows": 103121158177,
            "state_n_rows": 68736253954,
            "abs_upper_rows": 2749248839712,
            "block_bounds": 57376
          }
        },
        {
          "state_p_rows": [
            23,
            6,
            19,
            9
          ],
          "state_n_rows": [
            46,
            12,
            38,
            2
          ],
          "abs_upper_rows": [
            24,
            7,
            20,
            8
          ],
          "block_bounds": [
            24,
            20
          ],
          "max_error": 172,
          "certified": 1,
          "packed": {
            "state_p_rows": 77389115415,
            "state_n_rows": 17339277358,
            "abs_upper_rows": 4399388745752,
            "block_bounds": 163864
          }
        },
        {
          "state_p_rows": [
            22,
            3,
            10,
            30
          ],
          "state_n_rows": [
            44,
            2,
            20,
            60
          ],
          "abs_upper_rows": [
            23,
            2,
            11,
            31
          ],
          "block_bounds": [
            23,
            31
          ],
          "max_error": 185,
          "certified": 1,
          "packed": {
            "state_p_rows": 257739986966,
            "state_n_rows": 515479965740,
            "abs_upper_rows": 17043168444439,
            "block_bounds": 253975
          }
        },
        {
          "state_p_rows": [
            13,
            27,
            0,
            16
          ],
          "state_n_rows": [
            26,
            18,
            0,
            32
          ],
          "abs_upper_rows": [
            14,
            10,
            1,
            17
          ],
          "block_bounds": [
            14,
            17
          ],
          "max_error": 183,
          "certified": 1,
          "packed": {
            "state_p_rows": 137439008781,
            "state_n_rows": 274877943834,
            "abs_upper_rows": 9345916026894,
            "block_bounds": 139278
          }
        }
      ],
      "converged": 1,
      "continue": 0
    },
    {
      "iter": 1,
      "clusters": [
        {
          "state_p_rows": [
            58,
            28,
            21,
            25
          ],
          "state_n_rows": [
            36,
            26,
            26,
            50
          ],
          "abs_upper_rows": [
            21,
            8,
            8,
            17
          ],
          "block_bounds": [
            21,
            17
          ],
          "max_error": 211,
          "certified": 1,
          "packed": {
            "state_p_rows": 214836502586,
            "state_n_rows": 429605834788,
            "abs_upper_rows": 9346385772565,
            "block_bounds": 139285
          }
        },
        {
          "state_p_rows": [
            52,
            35,
            45,
            22
          ],
          "state_n_rows": [
            84,
            2,
            2,
            8
          ],
          "abs_upper_rows": [
            23,
            23,
            21,
            10
          ],
          "block_bounds": [
            23,
            21
          ],
          "max_error": 178,
          "certified": 1,
          "packed": {
            "state_p_rows": 189167376436,
            "state_n_rows": 68727869524,
            "abs_upper_rows": 5498967613463,
            "block_bounds": 172055
          }
        },
        {
          "state_p_rows": [
            44,
            32,
            59,
            5
          ],
          "state_n_rows": [
            72,
            64,
            82,
            10
          ],
          "abs_upper_rows": [
            38,
            43,
            25,
            6
          ],
          "block_bounds": [
            43,
            25
          ],
          "max_error": 494,
          "certified": 1,
          "packed": {
            "state_p_rows": 43197202476,
            "state_n_rows": 86243409992,
            "abs_upper_rows": 3300212957222,
            "block_bounds": 204843
          }
        },
        {
          "state_p_rows": [
            106,
            62,
            45,
            35
          ],
          "state_n_rows": [
            68,
            36,
            18,
            2
          ],
          "abs_upper_rows": [
            25,
            13,
            19,
            5
          ],
          "block_bounds": [
            25,
            19
          ],
          "max_error": 339,
          "certified": 1,
          "packed": {
            "state_p_rows": 300836581482,
            "state_n_rows": 17255440452,
            "abs_upper_rows": 2750054244377,
            "block_bounds": 155673
          }
        },
        {
          "state_p_rows": [
            90,
            50,
            9,
            5
          ],
          "state_n_rows": [
            32,
            36,
            2,
            10
          ],
          "abs_upper_rows": [
            28,
            15,
            2,
            10
          ],
          "block_bounds": [
            28,
            10
          ],
          "max_error": 226,
          "certified": 1,
          "packed": {
            "state_p_rows": 42987524186,
            "state_n_rows": 85907808288,
            "abs_upper_rows": 5497692479516,
            "block_bounds": 81948
          }
        },
        {
          "state_p_rows": [
            31,
            55,
            6,
            11
          ],
          "state_n_rows": [
            62,
            46,
            46,
            2
          ],
          "abs_upper_rows": [
            9,
            16,
            22,
            3
          ],
          "block_bounds": [
            16,
            22
          ],
          "max_error": 158,
          "certified": 1,
          "packed": {
            "state_p_rows": 94514559007,
            "state_n_rows": 17372901438,
            "abs_upper_rows": 1650743967753,
            "block_bounds": 180240
          }
        },
        {
          "state_p_rows": [
            11,
            8,
            21,
            74
          ],
          "state_n_rows": [
            46,
            16,
            42,
            60
          ],
          "abs_upper_rows": [
            14,
            10,
            12,
            45
          ],
          "block_bounds": [
            14,
            45
          ],
          "max_error": 208,
          "certified": 1,
          "packed": {
            "state_p_rows": 635743256587,
            "state_n_rows": 515572269102,
            "abs_upper_rows": 24739817013262,
            "block_bounds": 368654
          }
        },
        {
          "state_p_rows": [
            14,
            63,
            59,
            35
          ],
          "state_n_rows": [
            26,
            42,
            82,
            34
          ],
          "abs_upper_rows": [
            2,
            13,
            24,
            18
          ],
          "block_bounds": [
            13,
            24
          ],
          "max_error": 211,
          "certified": 1,
          "packed": {
            "state_p_rows": 300895303694,
            "state_n_rows": 292401795098,
            "abs_upper_rows": 9897215369218,
            "block_bounds": 196621
          }
        }
      ],
      "converged": 1,
      "continue": 0
    },
    {
      "iter": 2,
      "clusters": [
        {
          "state_p_rows": [
            49,
            1,
            57,
            4
          ],
          "state_n_rows": [
            34,
            10,
            58,
            10
          ],
          "abs_upper_rows": [
            8,
            12,
            5,
            20
          ],
          "block_bounds": [
            12,
            20
          ],
          "max_error": 172,
          "certified": 1,
          "packed": {
            "state_p_rows": 34598815793,
            "state_n_rows": 86142636066,
            "abs_upper_rows": 10995451920392,
            "block_bounds": 163852
          }
        },
        {
          "state_p_rows": [
            4,
            62,
            38,
            15
          ],
          "state_n_rows": [
            20,
            40,
            8,
            10
          ],
          "abs_upper_rows": [
            17,
            12,
            14,
            10
          ],
          "block_bounds": [
            17,
            14
          ],
          "max_error": 127,
          "certified": 1,
          "packed": {
            "state_p_rows": 129008529412,
            "state_n_rows": 85932982292,
            "abs_upper_rows": 5498497761297,
            "block_bounds": 114705
          }
        },
        {
          "state_p_rows": [
            21,
            26,
            55,
            5
          ],
          "state_n_rows": [
            34,
            36,
            42,
            10
          ],
          "abs_upper_rows": [
            16,
            23,
            37,
            1
          ],
          "block_bounds": [
            23,
            37
          ],
          "max_error": 406,
          "certified": 1,
          "packed": {
            "state_p_rows": 43180412949,
            "state_n_rows": 86075580450,
            "abs_upper_rows": 552239030288,
            "block_bounds": 303127
          }
        },
        {
          "state_p_rows": [
            113,
            31,
            20,
            33
          ],
          "state_n_rows": [
            66,
            10,
            8,
            2
          ],
          "abs_upper_rows": [
            10,
            6,
            16,
            3
          ],
          "block_bounds": [
            10,
            16
          ],
          "max_error": 186,
          "certified": 1,
          "packed": {
            "state_p_rows": 283551791217,
            "state_n_rows": 17213444162,
            "abs_upper_rows": 1650341232650,
            "block_bounds": 131082
          }
        },
        {
          "state_p_rows": [
            93,
            30,
            9,
            18
          ],
          "state_n_rows": [
            34,
            20,
            2,
            4
          ],
          "abs_upper_rows": [
            2,
            5,
            1,
            20
          ],
          "block_bounds": [
            5,
            20
          ],
          "max_error": 150,
          "certified": 1,
          "packed": {
            "state_p_rows": 154656632925,
            "state_n_rows": 34368167970,
            "abs_upper_rows": 10995183427586,
            "block_bounds": 163845
          }
        },
        {
          "state_p_rows": [
            39,
            103,
            25,
            18
          ],
          "state_n_rows": [
            46,
            78,
            54,
            0
          ],
          "abs_upper_rows": [
            25,
            17,
            12,
            10
          ],
          "block_bounds": [
            25,
            12
          ],
          "max_error": 149,
          "certified": 1,
          "packed": {
            "state_p_rows": 154723891239,
            "state_n_rows": 226652206,
            "abs_upper_rows": 5498363584537,
            "block_bounds": 98329
          }
        },
        {
          "state_p_rows": [
            33,
            5,
            18,
            40
          ],
          "state_n_rows": [
            42,
            2,
            20,
            52
          ],
          "abs_upper_rows": [
            27,
            12,
            20,
            27
          ],
          "block_bounds": [
            27,
            27
          ],
          "max_error": 189,
          "certified": 1,
          "packed": {
            "state_p_rows": 343672891425,
            "state_n_rows": 446760489002,
            "abs_upper_rows": 14844749250587,
            "block_bounds": 221211
          }
        },
        {
          "state_p_rows": [
            8,
            24,
            2,
            114
          ],
          "state_n_rows": [
            26,
            16,
            4,
            100
          ],
          "abs_upper_rows": [
            7,
            14,
            22,
            14
          ],
          "block_bounds": [
            14,
            22
          ],
          "max_error": 208,
          "certified": 1,
          "packed": {
            "state_p_rows": 979260981256,
            "state_n_rows": 859010269210,
            "abs_upper_rows": 7698057904135,
            "block_bounds": 180238
          }
        }
      ],
      "converged": 1,
      "continue": 0
    },
    {
      "iter": 3,
      "clusters": [
        {
          "state_p_rows": [
            101,
            40,
            10,
            12
          ],
          "state_n_rows": [
            66,
            74,
            20,
            26
          ],
          "abs_upper_rows": [
            21,
            26,
            10,
            9
          ],
          "block_bounds": [
            26,
            10
          ],
          "max_error": 206,
          "certified": 1,
          "packed": {
            "state_p_rows": 103121240165,
            "state_n_rows": 223422337090,
            "abs_upper_rows": 4948473626645,
            "block_bounds": 81946
          }
        },
        {
          "state_p_rows": [
            58,
            62,
            36,
            22
          ],
          "state_n_rows": [
            52,
            40,
            0,
            8
          ],
          "abs_upper_rows": [
            23,
            1,
            7,
            10
          ],
          "block_bounds": [
            23,
            10
          ],
          "max_error": 145,
          "certified": 1,
          "packed": {
            "state_p_rows": 189129683002,
            "state_n_rows": 68719558708,
            "abs_upper_rows": 5498027909143,
            "block_bounds": 81943
          }
        },
        {
          "state_p_rows": [
            56,
            34,
            8,
            10
          ],
          "state_n_rows": [
            80,
            68,
            16,
            20
          ],
          "abs_upper_rows": [
            12,
            25,
            22,
            6
          ],
          "block_bounds": [
            25,
            22
          ],
          "max_error": 332,
          "certified": 1,
          "packed": {
            "state_p_rows": 85932970040,
            "state_n_rows": 171865940048,
            "abs_upper_rows": 3300011483148,
            "block_bounds": 180249
          }
        },
        {
          "state_p_rows": [
            102,
            23,
            114,
            50
          ],
          "state_n_rows": [
            68,
            10,
            64,
            0
          ],
          "abs_upper_rows": [
            14,
            9,
            39,
            20
          ],
          "block_bounds": [
            14,
            39
          ],
          "max_error": 360,
          "certified": 1,
          "packed": {
            "state_p_rows": 429974927462,
            "state_n_rows": 268456004,
            "abs_upper_rows": 10997733597198,
            "block_bounds": 319502
          }
        },
        {
          "state_p_rows": [
            54,
            110,
            9,
            18
          ],
          "state_n_rows": [
            8,
            84,
            2,
            4
          ],
          "abs_upper_rows": [
            14,
            17,
            1,
            1
          ],
          "block_bounds": [
            17,
            1
          ],
          "max_error": 122,
          "certified": 1,
          "packed": {
            "state_p_rows": 154656796726,
            "state_n_rows": 34368299016,
            "abs_upper_rows": 549823062030,
            "block_bounds": 8209
          }
        },
        {
          "state_p_rows": [
            38,
            0,
            22,
            116
          ],
          "state_n_rows": [
            46,
            4,
            46,
            96
          ],
          "abs_upper_rows": [
            2,
            30,
            6,
            3
          ],
          "block_bounds": [
            30,
            6
          ],
          "max_error": 162,
          "certified": 1,
          "packed": {
            "state_p_rows": 996524687398,
            "state_n_rows": 824826667054,
            "abs_upper_rows": 1649670340610,
            "block_bounds": 49182
          }
        },
        {
          "state_p_rows": [
            6,
            26,
            11,
            43
          ],
          "state_n_rows": [
            44,
            16,
            22,
            62
          ],
          "abs_upper_rows": [
            30,
            8,
            10,
            8
          ],
          "block_bounds": [
            30,
            10
          ],
          "max_error": 150,
          "certified": 1,
          "packed": {
            "state_p_rows": 369413378054,
            "state_n_rows": 532668252204,
            "abs_upper_rows": 4398717665310,
            "block_bounds": 81950
          }
        },
        {
          "state_p_rows": [
            13,
            27,
            0,
            16
          ],
          "state_n_rows": [
            26,
            18,
            0,
            32
          ],
          "abs_upper_rows": [
            6,
            2,
            3,
            31
          ],
          "block_bounds": [
            6,
            31
          ],
          "max_error": 216,
          "certified": 1,
          "packed": {
            "state_p_rows": 137439008781,
            "state_n_rows": 274877943834,
            "abs_upper_rows": 17042631573510,
            "block_bounds": 253958
          }
        }
      ],
      "converged": 1,
      "continue": 0
    },
    {
      "iter": 4,
      "clusters": [
        {
          "state_p_rows": [
            6,
            23,
            22,
            9
          ],
          "state_n_rows": [
            4,
            46,
            28,
            18
          ],
          "abs_upper_rows": [
            34,
            12,
            5,
            6
          ],
          "block_bounds": [
            34,
            6
          ],
          "max_error": 234,
          "certified": 1,
          "packed": {
            "state_p_rows": 77401733126,
            "state_n_rows": 154736357380,
            "abs_upper_rows": 3298870525986,
            "block_bounds": 49186
          }
        },
        {
          "state_p_rows": [
            10,
            29,
            57,
            15
          ],
          "state_n_rows": [
            20,
            18,
            34,
            10
          ],
          "abs_upper_rows": [
            17,
            12,
            14,
            10
          ],
          "block_bounds": [
            17,
            14
          ],
          "max_error": 127,
          "certified": 1,
          "packed": {
            "state_p_rows": 129088153610,
            "state_n_rows": 86041989140,
            "abs_upper_rows": 5498497761297,
            "block_bounds": 114705
          }
        },
        {
          "state_p_rows": [
            27,
            30,
            3,
            18
          ],
          "state_n_rows": [
            18,
            20,
            2,
            20
          ],
          "abs_upper_rows": [
            34,
            45,
            10,
            9
          ],
          "block_bounds": [
            45,
            10
          ],
          "max_error": 420,
          "certified": 1,
          "packed": {
            "state_p_rows": 154631467035,
            "state_n_rows": 171807121426,
            "abs_upper_rows": 4948473782306,
            "block_bounds": 81965
          }
        },
        {
          "state_p_rows": [
            21,
            18,
            18,
            48
          ],
          "state_n_rows": [
            2,
            4,
            0,
            0
          ],
          "abs_upper_rows": [
            16,
            2,
            33,
            3
          ],
          "block_bounds": [
            16,
            33
          ],
          "max_error": 342,
          "certified": 1,
          "packed": {
            "state_p_rows": 412392394773,
            "state_n_rows": 8194,
            "abs_upper_rows": 1651482050576,
            "block_bounds": 270352
          }
        },
        {
          "state_p_rows": [
            32,
            52,
            10,
            18
          ],
          "state_n_rows": [
            0,
            40,
            4,
            4
          ],
          "abs_upper_rows": [
            15,
            15,
            2,
            1
          ],
          "block_bounds": [
            15,
            2
          ],
          "max_error": 111,
          "certified": 1,
          "packed": {
            "state_p_rows": 154660872224,
            "state_n_rows": 34376597504,
            "abs_upper_rows": 549890154511,
            "block_bounds": 16399
          }
        },
        {
          "state_p_rows": [
            124,
            6,
            19,
            9
          ],
          "state_n_rows": [
            122,
            12,
            38,
            2
          ],
          "abs_upper_rows": [
            11,
            3,
            6,
            14
          ],
          "block_bounds": [
            11,
            14
          ],
          "max_error": 103,
          "certified": 1,
          "packed": {
            "state_p_rows": 77389115516,
            "state_n_rows": 17339277434,
            "abs_upper_rows": 7696984072203,
            "block_bounds": 114699
          }
        },
        {
          "state_p_rows": [
            40,
            26,
            50,
            126
          ],
          "state_n_rows": [
            52,
            16,
            52,
            124
          ],
          "abs_upper_rows": [
            27,
            1,
            10,
            22
          ],
          "block_bounds": [
            27,
            22
          ],
          "max_error": 174,
          "certified": 1,
          "packed": {
            "state_p_rows": 1082541527080,
            "state_n_rows": 1065370026036,
            "abs_upper_rows": 12095299002395,
            "block_bounds": 180251
          }
        },
        {
          "state_p_rows": [
            99,
            26,
            59,
            35
          ],
          "state_n_rows": [
            86,
            16,
            82,
            34
          ],
          "abs_upper_rows": [
            27,
            2,
            24,
            18
          ],
          "block_bounds": [
            27,
            24
          ],
          "max_error": 309,
          "certified": 1,
          "packed": {
            "state_p_rows": 300895228003,
            "state_n_rows": 292401741910,
            "abs_upper_rows": 9897215279131,
            "block_bounds": 196635
          }
        }
      ],
      "converged": 1,
      "continue": 0
    },
    {
      "iter": 5,
      "clusters": [
        {
          "state_p_rows": [
            58,
            28,
            21,
            25
          ],
          "state_n_rows": [
            36,
            26,
            26,
            50
          ],
          "abs_upper_rows": [
            21,
            26,
            2,
            17
          ],
          "block_bounds": [
            26,
            17
          ],
          "max_error": 241,
          "certified": 1,
          "packed": {
            "state_p_rows": 214836502586,
            "state_n_rows": 429605834788,
            "abs_upper_rows": 9345983266837,
            "block_bounds": 139290
          }
        },
        {
          "state_p_rows": [
            52,
            35,
            45,
            22
          ],
          "state_n_rows": [
            84,
            2,
            2,
            8
          ],
          "abs_upper_rows": [
            23,
            23,
            21,
            10
          ],
          "block_bounds": [
            23,
            21
          ],
          "max_error": 178,
          "certified": 1,
          "packed": {
            "state_p_rows": 189167376436,
            "state_n_rows": 68727869524,
            "abs_upper_rows": 5498967613463,
            "block_bounds": 172055
          }
        },
        {
          "state_p_rows": [
            44,
            32,
            20,
            2
          ],
          "state_n_rows": [
            72,
            64,
            40,
            20
          ],
          "abs_upper_rows": [
            38,
            43,
            22,
            17
          ],
          "block_bounds": [
            43,
            22
          ],
          "max_error": 476,
          "certified": 1,
          "packed": {
            "state_p_rows": 17263820844,
            "state_n_rows": 171966595144,
            "abs_upper_rows": 9347325583398,
            "block_bounds": 180267
          }
        },
        {
          "state_p_rows": [
            20,
            26,
            41,
            39
          ],
          "state_n_rows": [
            0,
            4,
            18,
            10
          ],
          "abs_upper_rows": [
            2,
            9,
            6,
            20
          ],
          "block_bounds": [
            9,
            20
          ],
          "max_error": 201,
          "certified": 1,
          "packed": {
            "state_p_rows": 335179468820,
            "state_n_rows": 85974851584,
            "abs_upper_rows": 10995519004674,
            "block_bounds": 163849
          }
        },
        {
          "state_p_rows": [
            33,
            0,
            10,
            12
          ],
          "state_n_rows": [
            2,
            0,
            4,
            8
          ],
          "abs_upper_rows": [
            2,
            13,
            1,
            11
          ],
          "block_bounds": [
            13,
            11
          ],
          "max_error": 124,
          "certified": 1,
          "packed": {
            "state_p_rows": 103121158177,
            "state_n_rows": 68736253954,
            "abs_upper_rows": 6047381168130,
            "block_bounds": 90125
          }
        },
        {
          "state_p_rows": [
            31,
            31,
            22,
            16
          ],
          "state_n_rows": [
            62,
            30,
            46,
            0
          ],
          "abs_upper_rows": [
            34,
            8,
            6,
            10
          ],
          "block_bounds": [
            34,
            10
          ],
          "max_error": 190,
          "certified": 1,
          "packed": {
            "state_p_rows": 137531291679,
            "state_n_rows": 192999486,
            "abs_upper_rows": 5497960857634,
            "block_bounds": 81954
          }
        },
        {
          "state_p_rows": [
            1,
            8,
            8,
            44
          ],
          "state_n_rows": [
            42,
            16,
            20,
            60
          ],
          "abs_upper_rows": [
            30,
            19,
            11,
            19
          ],
          "block_bounds": [
            30,
            19
          ],
          "max_error": 177,
          "certified": 1,
          "packed": {
            "state_p_rows": 377990692865,
            "state_n_rows": 515479994410,
            "abs_upper_rows": 10446098817054,
            "block_bounds": 155678
          }
        },
        {
          "state_p_rows": [
            30,
            60,
            13,
            39
          ],
          "state_n_rows": [
            58,
            40,
            10,
            42
          ],
          "abs_upper_rows": [
            42,
            11,
            27,
            5
          ],
          "block_bounds": [
            42,
            27
          ],
          "max_error": 429,
          "certified": 1,
          "packed": {
            "state_p_rows": 335062097950,
            "state_n_rows": 360819277882,
            "abs_upper_rows": 2750591098922,
            "block_bounds": 221226
          }
        }
      ],
      "converged": 1,
      "continue": 0
    }
  ]
}